MANIFEST.in
README.md
requirements.txt
setup.cfg
setup.py
cocktail_shaker/__init__.py
cocktail_shaker/__main__.py
cocktail_shaker/cli.py
cocktail_shaker/file_handler.py
cocktail_shaker/functional_group_enumerator.py
cocktail_shaker/peptide_builder.py
cocktail_shaker/request_handler.py
cocktail_shaker/test.py
cocktail_shaker/validation.py
cocktail_shaker.egg-info/PKG-INFO
cocktail_shaker.egg-info/SOURCES.txt
cocktail_shaker.egg-info/dependency_links.txt
cocktail_shaker.egg-info/entry_points.txt
cocktail_shaker.egg-info/not-zip-safe
cocktail_shaker.egg-info/requires.txt
cocktail_shaker.egg-info/top_level.txt