Metadata-Version: 2.1
Name: cocktail-shaker
Version: 1.1.8
Summary: UNKNOWN
Home-page: https://www.github.com/Sulstice/Cocktail-Shaker
Author: Suliman Sharif
Author-email: sharifsuliman1@gmail.com
License: MIT
Keywords: cocktail chemistry ligand-design shaker
Platform: UNKNOWN
Classifier: Development Status :: 4 - Beta
Classifier: Natural Language :: English
Classifier: License :: OSI Approved :: MIT License
Classifier: Intended Audience :: Developers
Classifier: Programming Language :: Python :: 3
Classifier: Programming Language :: Python :: 3.3
Classifier: Programming Language :: Python :: 3.4
Classifier: Programming Language :: Python :: 3.5
Classifier: Programming Language :: Python :: 3.6
Classifier: Programming Language :: Python :: 3.7
